mdmpy/__init__.py
mdmpy/mdm.py
mdmpy/util.py
mdmpy-0.0.15.18.dist-info/LICENSE
mdmpy-0.0.15.18.dist-info/METADATA
mdmpy-0.0.15.18.dist-info/WHEEL
mdmpy-0.0.15.18.dist-info/RECORD
