Metadata-Version: 2.1
Name: mdmpy
Version: 0.0.15.18
Summary: 
License: MIT
Author: justanothergithubber
Author-email: 3600019+justanothergithubber@users.noreply.github.com
Requires-Python: >=3.11,<3.13
Classifier: License :: OSI Approved :: MIT License
Classifier: Programming Language :: Python :: 3
Classifier: Programming Language :: Python :: 3.11
Requires-Dist: Pyomo (>=6.6.1,<7.0.0)
Requires-Dist: numpy (>=1.25.0,<2.0.0)
Requires-Dist: pandas (>=2.0.3,<3.0.0)
Requires-Dist: scipy (>=1.11.1,<2.0.0)
